LICENSE.txt
README.md
setup.py
mychatgpt/__init__.py
mychatgpt/agents.py
mychatgpt/assistants.py
mychatgpt/gemini.py
mychatgpt/main.py
mychatgpt/utils.py
mychatgpt.egg-info/PKG-INFO
mychatgpt.egg-info/SOURCES.txt
mychatgpt.egg-info/dependency_links.txt
mychatgpt.egg-info/requires.txt
mychatgpt.egg-info/top_level.txt
tests/test.py