Metadata-Version: 2.1
Name: mychatgpt
Version: 0.4.7
Summary: mychatgpt is a small and useful Python module that provides functions for interacting with OpenAI's GPT models to create conversational agents. This module allows users to have interactive conversations with the GPT models and keeps track of the conversation history in your Python Projects and Jupyter Notebooks.
Home-page: https://github.com/johndef64/mychatgpt
Author: JohnDef64
Classifier: Programming Language :: Python :: 3
Classifier: License :: OSI Approved :: MIT License
Classifier: Operating System :: OS Independent
Requires-Python: >=3.6
License-File: LICENSE.txt
Requires-Dist: openai
Requires-Dist: tiktoken
Requires-Dist: langdetect
Requires-Dist: pandas
Requires-Dist: pyperclip
Requires-Dist: gdown
Requires-Dist: pyyaml
Requires-Dist: scipy
Requires-Dist: nltk
Requires-Dist: PyPDF2
Requires-Dist: cryptography
Requires-Dist: matplotlib
Requires-Dist: pygame
Requires-Dist: sounddevice
Requires-Dist: soundfile
Requires-Dist: keyboard
Requires-Dist: markdown
Requires-Dist: pillow
Requires-Dist: ollama
Requires-Dist: beautifulsoup4
Requires-Dist: googlesearch-python
Requires-Dist: tabulate
